package/__init__.py
package/main.py
package/order_management.py
package/user_management.py
finalHWcringe-0.9.3.dist-info/METADATA
finalHWcringe-0.9.3.dist-info/WHEEL
finalHWcringe-0.9.3.dist-info/entry_points.txt
finalHWcringe-0.9.3.dist-info/top_level.txt
finalHWcringe-0.9.3.dist-info/RECORD
