Metadata-Version: 2.1
Name: finalHWcringe
Version: 0.9.3
Summary: applications for managing orders and users.
Author-email: osisochka <a.onufrienko@edu.centraluniversity.ru>
License: MIT
Requires-Python: >=3.6
Requires-Dist: pandas
